rocketqa/__init__.py
rocketqa/rocketqa.py
rocketqa/encoder/__init__.py
rocketqa/encoder/cross_encoder.py
rocketqa/encoder/dual_encoder.py
rocketqa/model/__init__.py
rocketqa/model/cross_encoder_predict.py
rocketqa/model/cross_encoder_train.py
rocketqa/model/dual_encoder_predict.py
rocketqa/model/dual_encoder_train.py
rocketqa/model/ernie.py
rocketqa/model/transformer_encoder.py
rocketqa/reader/__init__.py
rocketqa/reader/reader_ce_predict.py
rocketqa/reader/reader_ce_train.py
rocketqa/reader/reader_de_predict.py
rocketqa/reader/reader_de_train.py
rocketqa/utils/__init__.py
rocketqa/utils/args.py
rocketqa/utils/batching.py
rocketqa/utils/finetune_args.py
rocketqa/utils/init.py
rocketqa/utils/optimization.py
rocketqa/utils/tokenization.py
rocketqa-1.1.0.dist-info/LICENSE
rocketqa-1.1.0.dist-info/METADATA
rocketqa-1.1.0.dist-info/WHEEL
rocketqa-1.1.0.dist-info/top_level.txt
rocketqa-1.1.0.dist-info/RECORD
