Metadata-Version: 2.1
Name: rocketqa
Version: 1.1.0
Summary: RocketQA development tools and examples, building on top of PaddlePaddle2.0.
Home-page: https://github.com/PaddlePaddle/RocketQA
Author: dingyuchen
Author-email: dingyuchen@baidu.com
License: Apache 2.0
Platform: UNKNOWN
Classifier: Programming Language :: Python :: 3
Classifier: Programming Language :: Python :: 3.6
Classifier: Programming Language :: Python :: 3.7
Classifier: Programming Language :: Python :: 3.8
Classifier: License :: OSI Approved :: Apache Software License
Classifier: Operating System :: OS Independent
Requires-Python: >=3.6
Requires-Dist: tqdm
